flask_webpackext/__init__.py
flask_webpackext/bundle.py
flask_webpackext/cli.py
flask_webpackext/config.py
flask_webpackext/errors.py
flask_webpackext/ext.py
flask_webpackext/manifest.py
flask_webpackext/project.py
flask_webpackext/proxies.py
flask_webpackext-2.1.0.dist-info/licenses/AUTHORS.rst
flask_webpackext-2.1.0.dist-info/licenses/LICENSE
flask_webpackext-2.1.0.dist-info/METADATA
flask_webpackext-2.1.0.dist-info/WHEEL
flask_webpackext-2.1.0.dist-info/entry_points.txt
flask_webpackext-2.1.0.dist-info/top_level.txt
flask_webpackext-2.1.0.dist-info/RECORD
