Metadata-Version: 2.4
Name: flask-webpackext
Version: 2.1.0
Summary: Webpack integration for Flask.
Home-page: https://github.com/inveniosoftware/flask-webpackext
Author: CERN
Author-email: info@inveniosoftware.org
License: BSD
Keywords: flask webpack
Platform: any
Classifier: Development Status :: 5 - Production/Stable
Requires-Python: >=3.7
License-File: LICENSE
License-File: AUTHORS.rst
Requires-Dist: Flask>=0.11
Requires-Dist: pywebpack<3.0.0,>=2.1.0
Provides-Extra: tests
Requires-Dist: pytest-black-ng>=0.4.0; extra == "tests"
Requires-Dist: check-manifest>=0.25; extra == "tests"
Requires-Dist: coverage>=4.0; extra == "tests"
Requires-Dist: isort>=4.3.21; extra == "tests"
Requires-Dist: pydocstyle>=1.0.0; extra == "tests"
Requires-Dist: pytest-cache>=1.0; extra == "tests"
Requires-Dist: pytest-cov>=1.8.0; extra == "tests"
Requires-Dist: pytest>=2.8.0; extra == "tests"
Requires-Dist: sphinx>=4.5; extra == "tests"
Requires-Dist: sphinx-click>=1.4.0; extra == "tests"
Provides-Extra: docs
Dynamic: license-file
